{"cameraMode":{"drawMode":0,"name":"Shaded","section":"Shading Mode"},"sceneLighting":true,"audioPlay":false,"sceneViewState":{"m_AlwaysRefresh":false,"showFog":true,"showSkybox":true,"showFlares":true,"showImageEffects":true,"showParticleSystems":true,"showVisualEffectGraphs":true,"m_FxEnabled":true},"in2DMode":false,"pivot":{"x":-4.728744983673096,"y":30.082998275756837,"z":-29.015716552734376},"rotation":{"x":0.2521769106388092,"y":-0.10637766122817993,"z":0.027950169518589975,"w":0.9615111947059631},"size":10.0,"orthographic":false}