{"cameraMode":{"drawMode":0,"name":"Shaded","section":"Shading Mode"},"sceneLighting":true,"audioPlay":false,"sceneViewState":{"m_AlwaysRefresh":false,"showFog":true,"showSkybox":true,"showFlares":true,"showImageEffects":true,"showParticleSystems":true,"showVisualEffectGraphs":true,"m_FxEnabled":true},"in2DMode":false,"pivot":{"x":40.7540168762207,"y":10.042996406555176,"z":-12.55615520477295},"rotation":{"x":-0.01871744729578495,"y":0.938147783279419,"z":-0.027036376297473909,"w":-0.34618818759918215},"size":0.8660253882408142,"orthographic":false}