{"cameraMode":{"drawMode":0,"name":"Shaded","section":"Shading Mode"},"sceneLighting":false,"audioPlay":false,"sceneViewState":{"m_AlwaysRefresh":false,"showFog":true,"showSkybox":false,"showFlares":true,"showImageEffects":true,"showParticleSystems":true,"showVisualEffectGraphs":true,"m_FxEnabled":true},"in2DMode":false,"pivot":{"x":-0.2999972403049469,"y":9.017472267150879,"z":3.1316442489624025},"rotation":{"x":-0.28470876812934878,"y":0.27490678429603579,"z":-0.0854995921254158,"w":-0.9144395589828491},"size":0.4103758931159973,"orthographic":false}